[
    {
        "id": "mid",
        "name": "Министерство иностранных дел Российской Федерации",
        "shortName": "МИД России",
        "sphere": "political",
        "officialWebsite": "https://mid.ru"
    },
    {
        "id": "mincifry",
        "name": "Министерство цифрового развития, связи и массовых коммуникаций Российской Федерации",
        "shortName": "Минцифры России",
        "sphere": "economic",
        "officialWebsite": "https://digital.gov.ru"
    },
    {
        "id": "minzdrav",
        "name": "Министерство здравоохранения Российской Федерации",
        "shortName": "Минздрав России",
        "sphere": "social",
        "officialWebsite": "https://minzdrav.gov.ru"
    },
    {
        "id": "minobrnauki",
        "name": "Министерство науки и высшего образования Российской Федерации",
        "shortName": "Минобрнауки России",
        "sphere": "social",
        "officialWebsite": "https://minobrnauki.gov.ru"
    },
    {
        "id": "minsport",
        "name": "Министерство спорта Российской Федерации",
        "shortName": "Минспорт России",
        "sphere": "social",
        "officialWebsite": "https://www.minsport.gov.ru"
    },
    {
        "id": "mineconomy",
        "name": "Министерство экономического развития Российской Федерации",
        "shortName": "Минэкономразвития России",
        "sphere": "economic",
        "officialWebsite": "https://www.economy.gov.ru"
    },
    {
        "id": "ran",
        "name": "Российская академия наук",
        "shortName": "РАН",
        "sphere": "social",
        "officialWebsite": "https://www.ras.ru"
    },
    {
        "id": "minjust",
        "name": "Министерство юстиции Российской Федерации",
        "shortName": "Минюст России",
        "sphere": "political",
        "officialWebsite": "https://minjust.gov.ru"
    },
    {
        "id": "rosmolodezh",
        "name": "Федеральное агентство по делам молодежи",
        "shortName": "Росмолодежь",
        "sphere": "social",
        "officialWebsite": "https://fadm.gov.ru"
    },
    {
        "id": "rosgvardiya",
        "name": "Федеральная служба войск национальной гвардии Российской Федерации",
        "shortName": "Росгвардия",
        "sphere": "security",
        "officialWebsite": "https://rosguard.gov.ru"
    },
    {
        "id": "roszdravnadzor",
        "name": "Федеральная служба по надзору в сфере здравоохранения",
        "shortName": "Росздравнадзор",
        "sphere": "social",
        "officialWebsite": "https://roszdravnadzor.gov.ru"
    },
    {
        "id": "rosakkreditatsiya",
        "name": "Федеральная служба по аккредитации",
        "shortName": "Росаккредитация",
        "sphere": "economic",
        "officialWebsite": "https://fsa.gov.ru"
    },
    {
        "id": "rosreestr",
        "name": "Федеральная служба государственной регистрации, кадастра и картографии",
        "shortName": "Росреестр",
        "sphere": "economic",
        "officialWebsite": "https://rosreestr.gov.ru"
    },
    {
        "id": "mintrud",
        "name": "Министерство труда и социальной защиты Российской Федерации",
        "shortName": "Минтруд России",
        "sphere": "social",
        "officialWebsite": "https://mintrud.gov.ru"
    }
]
